<?xml version="1.0" encoding="UTF-8"?>
<DEFECTS>
  <DEFECT>
    <SFA>
      <FILEPATH>C:\Dev\third-party-dependencies\imgui\</FILEPATH>
      <FILENAME>imgui.cpp</FILENAME>
      <LINE>8492</LINE>
      <COLUMN>45</COLUMN>
    </SFA>
    <DEFECTCODE>33011</DEFECTCODE>
    <DESCRIPTION>Unchecked upper bound for enum key used as index..</DESCRIPTION>
    <FUNCTION>ImGui::GetKeyData</FUNCTION>
    <DECORATED>?GetKeyData@ImGui@@YAPEAUImGuiKeyData@@PEAUImGuiContext@@W4ImGuiKey@@@Z</DECORATED>
    <FUNCLINE>8482</FUNCLINE>
    <PATH></PATH>
  </DEFECT>
  <DEFECT>
    <SFA>
      <FILEPATH>C:\Dev\third-party-dependencies\imgui\</FILEPATH>
      <FILENAME>imgui.cpp</FILENAME>
      <LINE>9557</LINE>
      <COLUMN>4</COLUMN>
    </SFA>
    <DEFECTCODE>33010</DEFECTCODE>
    <DESCRIPTION>Unchecked lower bound for enum source used as index..</DESCRIPTION>
    <FUNCTION>GetInputSourceName</FUNCTION>
    <DECORATED>?GetInputSourceName@@YAPEBDW4ImGuiInputSource@@@Z</DECORATED>
    <FUNCLINE>9553</FUNCLINE>
    <PATH></PATH>
  </DEFECT>
  <DEFECT>
    <SFA>
      <FILEPATH>C:\Dev\third-party-dependencies\imgui\</FILEPATH>
      <FILENAME>imgui.cpp</FILENAME>
      <LINE>9563</LINE>
      <COLUMN>4</COLUMN>
    </SFA>
    <DEFECTCODE>33010</DEFECTCODE>
    <DESCRIPTION>Unchecked lower bound for enum source used as index..</DESCRIPTION>
    <FUNCTION>GetMouseSourceName</FUNCTION>
    <DECORATED>?GetMouseSourceName@@YAPEBDW4ImGuiMouseSource@@@Z</DECORATED>
    <FUNCLINE>9559</FUNCLINE>
    <PATH></PATH>
  </DEFECT>
  <DEFECT>
    <SFA>
      <FILEPATH>C:\Dev\third-party-dependencies\imgui\</FILEPATH>
      <FILENAME>imgui.cpp</FILENAME>
      <LINE>12227</LINE>
      <COLUMN>52</COLUMN>
    </SFA>
    <DEFECTCODE>6011</DEFECTCODE>
    <DESCRIPTION>Dereferencing NULL pointer 'window'. </DESCRIPTION>
    <FUNCTION>ImGui::NavCalcPreferredRefPos</FUNCTION>
    <DECORATED>?NavCalcPreferredRefPos@ImGui@@YA?AUImVec2@@XZ</DECORATED>
    <FUNCLINE>12202</FUNCLINE>
    <PROBABILITY>1</PROBABILITY>
    <RANK>4</RANK>
    <CATEGORY>
      <RULECATEGORY>mspft</RULECATEGORY>
    </CATEGORY>
    <PATH>
      <SFA>
        <FILEPATH>C:\Dev\third-party-dependencies\imgui\</FILEPATH>
        <FILENAME>imgui.cpp</FILENAME>
        <LINE>12204</LINE>
        <COLUMN>18</COLUMN>
      </SFA>
      <SFA>
        <FILEPATH>C:\Dev\third-party-dependencies\imgui\</FILEPATH>
        <FILENAME>imgui.cpp</FILENAME>
        <LINE>12205</LINE>
        <COLUMN>17</COLUMN>
      </SFA>
      <SFA>
        <FILEPATH>C:\Dev\third-party-dependencies\imgui\</FILEPATH>
        <FILENAME>imgui.cpp</FILENAME>
        <LINE>12206</LINE>
        <COLUMN>15</COLUMN>
      </SFA>
      <SFA>
        <FILEPATH>C:\Dev\third-party-dependencies\imgui\</FILEPATH>
        <FILENAME>imgui.cpp</FILENAME>
        <LINE>12209</LINE>
        <COLUMN>70</COLUMN>
        <KEYEVENT>
          <ID>1</ID>
          <KIND>branch</KIND>
          <IMPORTANCE>Full</IMPORTANCE>
          <MESSAGE>'window' may be NULL (Skip this branch)</MESSAGE>
        </KEYEVENT>
      </SFA>
      <SFA>
        <FILEPATH>C:\Dev\third-party-dependencies\imgui\</FILEPATH>
        <FILENAME>imgui.cpp</FILENAME>
        <LINE>12220</LINE>
        <COLUMN>15</COLUMN>
      </SFA>
      <SFA>
        <FILEPATH>C:\Dev\third-party-dependencies\imgui\</FILEPATH>
        <FILENAME>imgui.cpp</FILENAME>
        <LINE>12221</LINE>
        <COLUMN>12</COLUMN>
        <KEYEVENT>
          <ID>2</ID>
          <KIND>branch</KIND>
          <IMPORTANCE>Full</IMPORTANCE>
          <MESSAGE>Enter this branch, (assume 'activated_shortcut')</MESSAGE>
        </KEYEVENT>
      </SFA>
      <SFA>
        <FILEPATH>C:\Dev\third-party-dependencies\imgui\</FILEPATH>
        <FILENAME>imgui.cpp</FILENAME>
        <LINE>12222</LINE>
        <COLUMN>21</COLUMN>
      </SFA>
      <SFA>
        <FILEPATH>C:\Dev\third-party-dependencies\imgui\</FILEPATH>
        <FILENAME>imgui.cpp</FILENAME>
        <LINE>12227</LINE>
        <COLUMN>52</COLUMN>
        <KEYEVENT>
          <ID>3</ID>
          <KIND>branch</KIND>
          <IMPORTANCE>Full</IMPORTANCE>
          <MESSAGE>Skip this branch, (assume '&lt;branch condition&gt;' is false)</MESSAGE>
        </KEYEVENT>
      </SFA>
      <SFA>
        <FILEPATH>C:\Dev\third-party-dependencies\imgui\</FILEPATH>
        <FILENAME>imgui.cpp</FILENAME>
        <LINE>12227</LINE>
        <COLUMN>52</COLUMN>
        <KEYEVENT>
          <ID>4</ID>
          <KIND>usage</KIND>
          <IMPORTANCE>Essential</IMPORTANCE>
          <MESSAGE>'window' is dereferenced, but may still be NULL</MESSAGE>
        </KEYEVENT>
      </SFA>
    </PATH>
  </DEFECT>
</DEFECTS>